airflow_metaplane/get_provider_info.py
airflow_metaplane/mp_callbacks.py
airflow_metaplane/hooks/__init__.py
airflow_metaplane/hooks/metaplane_hook.py
airflow_metaplane/hooks/models.py
airflow_metaplane-0.0.6.dist-info/LICENSE
airflow_metaplane-0.0.6.dist-info/METADATA
airflow_metaplane-0.0.6.dist-info/WHEEL
airflow_metaplane-0.0.6.dist-info/entry_points.txt
airflow_metaplane-0.0.6.dist-info/top_level.txt
airflow_metaplane-0.0.6.dist-info/RECORD
