Metadata-Version: 2.1
Name: airflow-metaplane
Version: 0.0.6
Summary: Metaplane Airflow Provider
Author-email: Metaplane <engineering@metaplane.dev>
License: Apache License
Keywords: airflow-provider,metaplane,airflow,integration
Classifier: Framework :: Apache Airflow :: Provider
Classifier: License :: OSI Approved :: Apache Software License
Requires-Python: >=3.8
License-File: LICENSE
Requires-Dist: requests >=2.27.0
Requires-Dist: attrs >=22.1.0
Requires-Dist: cattrs >=22.1.0
Requires-Dist: apache-airflow >=2.0.0
Provides-Extra: test
Requires-Dist: black >=23.7.0 ; extra == 'test'
Requires-Dist: pre-commit ==2.15.0 ; extra == 'test'
Requires-Dist: pylint >=2.10.2 ; extra == 'test'
Requires-Dist: ruff >=0.0.285 ; extra == 'test'
Requires-Dist: mypy >=1.5.1 ; extra == 'test'
